README.rst
setup.py
example/__init__.py
example/app.py
example/controllers.py
example/model.py
spynach/__init__.py
spynach/application.py
spynach/authenticator.py
spynach/controller.py
spynach/mail_traceback.py
spynach/server.py
spynach/template.py
spynach/thread_locals.py
spynach.egg-info/PKG-INFO
spynach.egg-info/SOURCES.txt
spynach.egg-info/dependency_links.txt
spynach.egg-info/entry_points.txt
spynach.egg-info/not-zip-safe
spynach.egg-info/requires.txt
spynach.egg-info/top_level.txt